gitlab_to_sqlite/__init__.py
gitlab_to_sqlite/cli.py
gitlab_to_sqlite/utils.py
gitlab_to_sqlite-0.1.dist-info/LICENSE
gitlab_to_sqlite-0.1.dist-info/METADATA
gitlab_to_sqlite-0.1.dist-info/WHEEL
gitlab_to_sqlite-0.1.dist-info/entry_points.txt
gitlab_to_sqlite-0.1.dist-info/top_level.txt
gitlab_to_sqlite-0.1.dist-info/RECORD
