Metadata-Version: 2.1
Name: gitlab-to-sqlite
Version: 0.1
Summary: Save data from GitLab to a SQLite database.
Author: Reiner Gerecke
License: Apache-2.0
Project-URL: Homepage, https://github.com/squiddy/gitlab-to-sqlite
Project-URL: Changelog, https://github.com/squiddy/gitlab-to-sqlite/releases
Project-URL: Issues, https://github.com/squiddy/gitlab-to-sqlite/issues
Classifier: Development Status :: 3 - Alpha
License-File: LICENSE
Requires-Dist: sqlite-utils >=2.7.2
Requires-Dist: gql[all]
